refactron/__init__.py
refactron/cli.py
refactron/ai/__init__.py
refactron/analyzers/__init__.py
refactron/analyzers/base_analyzer.py
refactron/analyzers/code_smell_analyzer.py
refactron/analyzers/complexity_analyzer.py
refactron/analyzers/dead_code_analyzer.py
refactron/analyzers/dependency_analyzer.py
refactron/analyzers/performance_analyzer.py
refactron/analyzers/security_analyzer.py
refactron/analyzers/type_hint_analyzer.py
refactron/autofix/__init__.py
refactron/autofix/engine.py
refactron/autofix/file_ops.py
refactron/autofix/fixers.py
refactron/autofix/models.py
refactron/cicd/__init__.py
refactron/cicd/github_actions.py
refactron/cicd/gitlab_ci.py
refactron/cicd/pr_integration.py
refactron/cicd/pre_commit.py
refactron/cicd/quality_gates.py
refactron/core/__init__.py
refactron/core/analysis_result.py
refactron/core/backup.py
refactron/core/cache.py
refactron/core/config.py
refactron/core/config_loader.py
refactron/core/config_templates.py
refactron/core/config_validator.py
refactron/core/credentials.py
refactron/core/device_auth.py
refactron/core/exceptions.py
refactron/core/false_positive_tracker.py
refactron/core/incremental.py
refactron/core/logging_config.py
refactron/core/memory_profiler.py
refactron/core/metrics.py
refactron/core/models.py
refactron/core/parallel.py
refactron/core/prometheus_metrics.py
refactron/core/refactor_result.py
refactron/core/refactron.py
refactron/core/telemetry.py
refactron/multifile/__init__.py
refactron/patterns/__init__.py
refactron/patterns/fingerprint.py
refactron/patterns/learner.py
refactron/patterns/learning_service.py
refactron/patterns/matcher.py
refactron/patterns/models.py
refactron/patterns/ranker.py
refactron/patterns/storage.py
refactron/patterns/tuner.py
refactron/refactorers/__init__.py
refactron/refactorers/add_docstring_refactorer.py
refactron/refactorers/base_refactorer.py
refactron/refactorers/extract_method_refactorer.py
refactron/refactorers/magic_number_refactorer.py
refactron-1.0.14.dist-info/licenses/LICENSE
refactron-1.0.14.dist-info/METADATA
refactron-1.0.14.dist-info/WHEEL
refactron-1.0.14.dist-info/entry_points.txt
refactron-1.0.14.dist-info/top_level.txt
refactron-1.0.14.dist-info/RECORD
