Metadata-Version: 2.4
Name: refactron
Version: 1.0.14
Summary: Python code analysis and refactoring tool with security scanning, performance detection, and automated fixes
Author-email: Om Sherikar <omsherikar0229@gmail.com>
License: MIT
Project-URL: Homepage, https://refactron.dev
Project-URL: Documentation, https://docs.refactron.dev
Project-URL: Repository, https://github.com/Refactron-ai/Refactron_lib
Project-URL: Bug Tracker, https://github.com/Refactron-ai/Refactron_lib/issues
Keywords: refactoring,code-quality,static-analysis,code-optimization,technical-debt,code-review,security-analysis
Classifier: Development Status :: 5 - Production/Stable
Classifier: Intended Audience :: Developers
Classifier: Topic :: Software Development :: Quality Assurance
Classifier: Topic :: Software Development :: Libraries :: Python Modules
Classifier: License :: OSI Approved :: MIT License
Classifier: Programming Language :: Python :: 3
Classifier: Programming Language :: Python :: 3.8
Classifier: Programming Language :: Python :: 3.9
Classifier: Programming Language :: Python :: 3.10
Classifier: Programming Language :: Python :: 3.11
Classifier: Programming Language :: Python :: 3.12
Requires-Python: >=3.8
License-File: LICENSE
Requires-Dist: libcst>=1.1.0
Requires-Dist: click>=8.0.0
Requires-Dist: pyyaml>=6.0
Requires-Dist: rich>=13.0.0
Requires-Dist: radon>=6.0.0
Requires-Dist: requests>=2.25.0
Requires-Dist: astroid>=3.0.0
Provides-Extra: dev
Requires-Dist: pytest>=7.0.0; extra == "dev"
Requires-Dist: pytest-cov>=4.0.0; extra == "dev"
Requires-Dist: black>=23.0.0; extra == "dev"
Requires-Dist: mypy>=1.0.0; extra == "dev"
Requires-Dist: flake8>=6.0.0; extra == "dev"
Requires-Dist: isort>=5.12.0; extra == "dev"
Requires-Dist: types-requests; extra == "dev"
Requires-Dist: types-PyYAML; extra == "dev"
Dynamic: license-file
